{
    "title": "Chào mừng đến với Ngọc rồng PONY",
    "nameServer": "Ngọc Rồng PONY",
    "description": "Ngọc rồng PONY free all, mở thành viên, x99999 thỏi vàng,... ",
    "logoUrl": "/imgs/logo-nro-pony.png",
     "backgroundUrl": "/imgs/background/lionbg.jpg",
    "thongBao": {
        "is": true,
        "text": "<p class='text-center'>Chào mừng bạn đến với ngọc rồng PONY free all</p>-Server test vĩnh viễn không rerest<br/>-Cảm ơn bạn đã đọc thông báo<br/>-Chúc bạn chơi game vui vẻ"
    },
    "hotLink": [
        {
            "title": "Box Zalo",
            "text": "Tham nhóm zalo ngay",
            "href": "https://zalo.me/g/zokngv668"
        }
    ],
    "payment": {
        "atm": {
            "key": "VCB",
            "nameStk": "Vietcombank",
            "stk": "1052147418",
            "name": "Nguyen Kim Hien"
        },
        "card": {}
    }
}